tracetool/__init__.py
tracetool/tracetool.py
tracetool-12.5.0.dist-info/LICENSE.txt
tracetool-12.5.0.dist-info/METADATA
tracetool-12.5.0.dist-info/WHEEL
tracetool-12.5.0.dist-info/top_level.txt
tracetool-12.5.0.dist-info/RECORD
