Metadata-Version: 2.1
Name: tracetool
Version: 12.5.0
Summary: Tracetool Python package
Home-page: https://github.com/capslock66/Tracetool
Author: Thierry Parent
Author-email: none@gmail.com
Project-URL: Bug Tracker, https://github.com/capslock66/Tracetool/issues
Project-URL: repository, https://github.com/capslock66/Tracetool
Classifier: Programming Language :: Python :: 3
Classifier: License :: OSI Approved :: MIT License
Classifier: Operating System :: OS Independent
Requires-Python: >=2.6,>=3.1
License-File: LICENSE.txt
